PyP100/PyL530.py
PyP100/PyP100.py
PyP100/PyP110.py
PyP100/__init__.py
PyP100/tp_link_cipher.py
PyP100-0.1.1.dist-info/LICENSE.txt
PyP100-0.1.1.dist-info/METADATA
PyP100-0.1.1.dist-info/WHEEL
PyP100-0.1.1.dist-info/top_level.txt
PyP100-0.1.1.dist-info/RECORD
