Metadata-Version: 2.1
Name: PyP100
Version: 0.1.1
Summary: A module for controlling the Tp-link Tapo P100/P105/P110 plugs and L530/L510E bulbs.
Home-page: https://github.com/fishbigger/TapoP100
Author: Toby Johnson
Author-email: toby.e.m.Johnson@gmail.com
License: MIT
Download-URL: https://pypi.org/project/PyP100/
Keywords: Tapo,Tp-Link,P100
Platform: UNKNOWN
Requires-Dist: pkcs7 (>=0.1.2)
Requires-Dist: pycryptodome (>=3.9.8)
Requires-Dist: requests (>=2.24.0)
